{
  "name": "CorteizC-Star DenimJeans Jacket",
  "category": "Clothes",
  "subcategory": "",
  "best_batch": "GOAT",
  "best_batch_links": [
    {
      "label": "GOAT",
      "url": "https://litbuy.com/product/weidian/7653888327?inviteCode=REPTARO",
      "original_url": "https://oopbuy.com/product/weidian/7653888327?inviteCode=29TOTHGNH"
    }
  ],
  "budget_batch": "budget",
  "budget_batch_links": [
    {
      "label": "budget",
      "url": "https://litbuy.com/product/weidian/753388270425?inviteCode=REPTARO",
      "original_url": "https://www.oopbuy.com/product/0/753388270425?inviteCode=29TOTHGNH"
    }
  ],
  "best_price": "39$",
  "budget_price": "24$",
  "pics_text": "best/budget",
  "pics_links": [
    {
      "label": "best",
      "url": "https://goat-official.x.yupoo.com/albums/143652268?uid=1"
    },
    {
      "label": "budget",
      "url": "https://www.uufinds.com/goodItemDetail/qc/1939489382689009665?action=discord&cid=1942512167859859457"
    }
  ],
  "notes": "",
  "image_url": "https://docs.google.com/sheets-images-rt/AEjM2AzobyJJ8cB1L4UzLxmCPppcLhsM_hlllE7a2knww7KzrzvjYSFFHctp4Zn61edpo-fwBSSGI5gErLM0pKKfCBWCcq0tmihtEnKpCj6LAe8DOIlaJeL1_p2GheTep8v9e0n4KLTyVle5Nlqs=w143-h110",
  "local_image": "image.jpg",
  "folder": "clothes_0689",
  "raw_cells": {
    "col_0": {
      "text": "166"
    },
    "col_1": {
      "text": "CorteizC-Star DenimJeans Jacket"
    },
    "col_2": {
      "text": "",
      "image": "https://docs.google.com/sheets-images-rt/AEjM2AzobyJJ8cB1L4UzLxmCPppcLhsM_hlllE7a2knww7KzrzvjYSFFHctp4Zn61edpo-fwBSSGI5gErLM0pKKfCBWCcq0tmihtEnKpCj6LAe8DOIlaJeL1_p2GheTep8v9e0n4KLTyVle5Nlqs=w143-h110"
    },
    "col_3": {
      "text": "GOAT",
      "links": [
        {
          "label": "GOAT",
          "url": "https://oopbuy.com/product/weidian/7653888327?inviteCode=29TOTHGNH"
        }
      ]
    },
    "col_4": {
      "text": "budget",
      "links": [
        {
          "label": "budget",
          "url": "https://www.oopbuy.com/product/0/753388270425?inviteCode=29TOTHGNH"
        }
      ]
    },
    "col_5": {
      "text": "39$"
    },
    "col_6": {
      "text": "24$"
    },
    "col_7": {
      "text": "best/budget",
      "links": [
        {
          "label": "best",
          "url": "https://goat-official.x.yupoo.com/albums/143652268?uid=1"
        },
        {
          "label": "budget",
          "url": "https://www.uufinds.com/goodItemDetail/qc/1939489382689009665?action=discord&cid=1942512167859859457"
        }
      ]
    }
  }
}