{
  "name": "Balenciaga Laurel Shorts Black",
  "category": "Clothes",
  "subcategory": "",
  "best_batch": "JennyTurtle",
  "best_batch_links": [
    {
      "label": "JennyTurtle",
      "url": "https://litbuy.com/product/weidian/7431339379?inviteCode=REPTARO",
      "original_url": "https://oopbuy.com/product/weidian/7431339379?inviteCode=29TOTHGNH"
    }
  ],
  "budget_batch": "",
  "budget_batch_links": [],
  "best_price": "22$",
  "budget_price": "",
  "pics_text": "QC Pics",
  "pics_links": [
    {
      "label": "QC Pics",
      "url": "https://doppel.fit/item/weidian/7431339379"
    }
  ],
  "notes": "",
  "image_url": "https://docs.google.com/sheets-images-rt/AEjM2Ayd6NaRwAVJjyc6uLhuzNS7FjQhxRbtCy8SqOllnLigBXYRWsB4RCcV79gvBlpi84UB0NiqrEoGdvvh8HkDcHI8B1jPD5TyaFKtn9Q63Kq6BBDI7_W5tQUSg-3eC1S9=w143-h110",
  "local_image": "image.jpg",
  "folder": "clothes_1270",
  "raw_cells": {
    "col_0": {
      "text": "855"
    },
    "col_1": {
      "text": "Balenciaga Laurel Shorts Black"
    },
    "col_2": {
      "text": "",
      "image": "https://docs.google.com/sheets-images-rt/AEjM2Ayd6NaRwAVJjyc6uLhuzNS7FjQhxRbtCy8SqOllnLigBXYRWsB4RCcV79gvBlpi84UB0NiqrEoGdvvh8HkDcHI8B1jPD5TyaFKtn9Q63Kq6BBDI7_W5tQUSg-3eC1S9=w143-h110"
    },
    "col_3": {
      "text": "JennyTurtle",
      "links": [
        {
          "label": "JennyTurtle",
          "url": "https://oopbuy.com/product/weidian/7431339379?inviteCode=29TOTHGNH"
        }
      ]
    },
    "col_5": {
      "text": "22$"
    },
    "col_7": {
      "text": "QC Pics",
      "links": [
        {
          "label": "QC Pics",
          "url": "https://doppel.fit/item/weidian/7431339379"
        }
      ]
    }
  }
}