{
  "name": "Eric EmanuelNew YorkSunshine",
  "category": "Clothes",
  "subcategory": "",
  "best_batch": "Angelking",
  "best_batch_links": [
    {
      "label": "Angelking",
      "url": "https://litbuy.com/product/weidian/792718020125?inviteCode=REPTARO",
      "original_url": "https://weidian.com/item.html?itemID=792718020125"
    }
  ],
  "budget_batch": "UnionKingdom",
  "budget_batch_links": [
    {
      "label": "UnionKingdom",
      "url": "https://litbuy.com/product/weidian/800235190860?inviteCode=REPTARO",
      "original_url": "https://weidian.com/item.html?itemID=800235190860"
    }
  ],
  "best_price": "23$",
  "budget_price": "15$",
  "pics_text": "pics",
  "pics_links": [
    {
      "label": "pics",
      "url": "https://angelking47.x.yupoo.com/albums/121270008?uid=1&isSubCate=false&referrercate=3848500"
    }
  ],
  "notes": "",
  "image_url": "https://docs.google.com/sheets-images-rt/AEjM2AzXoicwmcqGigLI6B6n5M6uPN4tboGO1_JBhGrVm5xpYkJqymc1u7BZYTJ_VWG6UcbgjY9h46bEzfax8ooRdBwJgPxVIMZoQ-5oVsiAj85Xxsn14R3I_52oJOFuURRINX1x8dBSelBsgA=w143-h110",
  "local_image": "image.jpg",
  "folder": "clothes_1374",
  "raw_cells": {
    "col_0": {
      "text": "971"
    },
    "col_1": {
      "text": "Eric EmanuelNew YorkSunshine"
    },
    "col_2": {
      "text": "",
      "image": "https://docs.google.com/sheets-images-rt/AEjM2AzXoicwmcqGigLI6B6n5M6uPN4tboGO1_JBhGrVm5xpYkJqymc1u7BZYTJ_VWG6UcbgjY9h46bEzfax8ooRdBwJgPxVIMZoQ-5oVsiAj85Xxsn14R3I_52oJOFuURRINX1x8dBSelBsgA=w143-h110"
    },
    "col_3": {
      "text": "Angelking",
      "links": [
        {
          "label": "Angelking",
          "url": "https://litbuy.com/product/weidian/792718020125?inviteCode=REPTARO",
          "original_url": "https://weidian.com/item.html?itemID=792718020125"
        }
      ]
    },
    "col_4": {
      "text": "UnionKingdom",
      "links": [
        {
          "label": "UnionKingdom",
          "url": "https://litbuy.com/product/weidian/800235190860?inviteCode=REPTARO",
          "original_url": "https://weidian.com/item.html?itemID=800235190860"
        }
      ]
    },
    "col_5": {
      "text": "23$"
    },
    "col_6": {
      "text": "15$"
    },
    "col_7": {
      "text": "pics",
      "links": [
        {
          "label": "pics",
          "url": "https://angelking47.x.yupoo.com/albums/121270008?uid=1&isSubCate=false&referrercate=3848500"
        }
      ]
    }
  }
}