{
  "name": "Louis VuittonBracelet",
  "category": "Jewelry",
  "subcategory": "",
  "best_batch": "here",
  "best_batch_links": [
    {
      "label": "here",
      "url": "https://oopbuy.com/product/weidian/7258963765?inviteCode=29TOTHGNH",
      "original_url": null
    }
  ],
  "budget_batch": "",
  "budget_batch_links": [],
  "best_price": "58$",
  "budget_price": "",
  "pics_text": "QC Pics",
  "pics_links": [
    {
      "label": "QC Pics",
      "url": "https://doppel.fit/item/weidian/7258963765"
    }
  ],
  "notes": "",
  "image_url": "https://docs.google.com/sheets-images-rt/AEjM2AynovAb9zGQhtdzCr4LSEVufZiv66Z2eV8j2wfYjIqpdRWj-OeWu3BEgkw6ElMIB58TaThvoQKpd6IKXQc7KSUC2Gf-bcebXQdzngM4AHAaOvSYJXysqEfH8mDJ8LV3t6wqgclR-gOuGzi1=w143-h110",
  "raw_cells": {
    "col_0": {
      "text": "23"
    },
    "col_1": {
      "text": "Louis VuittonBracelet"
    },
    "col_2": {
      "text": "",
      "image": "https://docs.google.com/sheets-images-rt/AEjM2AynovAb9zGQhtdzCr4LSEVufZiv66Z2eV8j2wfYjIqpdRWj-OeWu3BEgkw6ElMIB58TaThvoQKpd6IKXQc7KSUC2Gf-bcebXQdzngM4AHAaOvSYJXysqEfH8mDJ8LV3t6wqgclR-gOuGzi1=w143-h110"
    },
    "col_3": {
      "text": "here",
      "links": [
        {
          "label": "here",
          "url": "https://oopbuy.com/product/weidian/7258963765?inviteCode=29TOTHGNH"
        }
      ]
    },
    "col_5": {
      "text": "58$"
    },
    "col_7": {
      "text": "QC Pics",
      "links": [
        {
          "label": "QC Pics",
          "url": "https://doppel.fit/item/weidian/7258963765"
        }
      ]
    }
  },
  "local_image": "image.jpg",
  "folder": "jewelry_1756"
}