{
  "name": "MertraTracksuitGrey/Black",
  "category": "Clothes",
  "subcategory": "",
  "best_batch": "firerep",
  "best_batch_links": [
    {
      "label": "firerep",
      "url": "https://litbuy.com/product/weidian/7594157553?inviteCode=REPTARO",
      "original_url": "https://weidian.com/item.html?itemID=7594157553"
    }
  ],
  "budget_batch": "budget",
  "budget_batch_links": [
    {
      "label": "budget",
      "url": "https://litbuy.com/product/weidian/947784824668?inviteCode=REPTARO",
      "original_url": "https://weidian.com/item.html?itemID=947784824668"
    }
  ],
  "best_price": "77$(SET)",
  "budget_price": "35$(SET)",
  "pics_text": "firerep/budget",
  "pics_links": [
    {
      "label": "firerep",
      "url": "https://firerep.x.yupoo.com/albums/205221435?uid=1&isSubCate=false&referrercate=4690816"
    },
    {
      "label": "budget",
      "url": "https://www.uufinds.com/goodItemDetail/qc/1979737239329529857?action=discord&type=1&cid=1942512167859859457"
    }
  ],
  "notes": "set 77$ - top 42$ - bottom 35$",
  "image_url": "https://docs.google.com/sheets-images-rt/AEjM2AwbQbexDOJWxRzJJENkbr1mhO-8i0ATrN53dFwpycfaAP2xn9jQRRSko2uC5Jm4jlNOuMJnFn7r4Wp3Zg-Bf9YTizMvxqARj9mmm4SnsM9PpbgtcXCgGAu_GKCaOfAgkVWuvhKxBQMB7kgh=w143-h110",
  "local_image": "image.jpg",
  "folder": "clothes_1093",
  "raw_cells": {
    "col_0": {
      "text": "640"
    },
    "col_1": {
      "text": "MertraTracksuitGrey/Black"
    },
    "col_2": {
      "text": "",
      "image": "https://docs.google.com/sheets-images-rt/AEjM2AwbQbexDOJWxRzJJENkbr1mhO-8i0ATrN53dFwpycfaAP2xn9jQRRSko2uC5Jm4jlNOuMJnFn7r4Wp3Zg-Bf9YTizMvxqARj9mmm4SnsM9PpbgtcXCgGAu_GKCaOfAgkVWuvhKxBQMB7kgh=w143-h110"
    },
    "col_3": {
      "text": "firerep",
      "links": [
        {
          "label": "firerep",
          "url": "https://litbuy.com/product/weidian/7594157553?inviteCode=REPTARO",
          "original_url": "https://weidian.com/item.html?itemID=7594157553"
        }
      ]
    },
    "col_4": {
      "text": "budget",
      "links": [
        {
          "label": "budget",
          "url": "https://litbuy.com/product/weidian/947784824668?inviteCode=REPTARO",
          "original_url": "https://weidian.com/item.html?itemID=947784824668"
        }
      ]
    },
    "col_5": {
      "text": "77$(SET)"
    },
    "col_6": {
      "text": "35$(SET)"
    },
    "col_7": {
      "text": "firerep/budget",
      "links": [
        {
          "label": "firerep",
          "url": "https://firerep.x.yupoo.com/albums/205221435?uid=1&isSubCate=false&referrercate=4690816"
        },
        {
          "label": "budget",
          "url": "https://www.uufinds.com/goodItemDetail/qc/1979737239329529857?action=discord&type=1&cid=1942512167859859457"
        }
      ]
    },
    "col_8": {
      "text": "set 77$ - top 42$ - bottom 35$"
    }
  }
}