{
  "name": "Tom Ford",
  "category": "Belts",
  "subcategory": "",
  "best_batch": "MissChen",
  "best_batch_links": [
    {
      "label": "MissChen",
      "url": "https://litbuy.com/product/weidian/6078351381?inviteCode=REPTARO",
      "original_url": "https://www.oopbuy.com/product/weidian/6078351381?inviteCode=29TOTHGNH"
    }
  ],
  "budget_batch": "",
  "budget_batch_links": [],
  "best_price": "36$",
  "budget_price": "",
  "pics_text": "QC Pics",
  "pics_links": [
    {
      "label": "QC Pics",
      "url": "https://www.uufinds.com/goodItemDetail/qc/1920323066922610690?action=discord&type=1&cid=1942512167859859457"
    }
  ],
  "notes": "",
  "image_url": "https://docs.google.com/sheets-images-rt/AEjM2AxQVAkFSQvaFpCCmxGfiX5F162ygC3DMbEPZ84QF5gIcvViJlgGX_coMD6tsHWmTM8jkTWgN8JXU29ttvSKUPBjhy3KvKpIOxXKELq3D4wSBPgisf0rqt678ojZHQz1eFjM_OlwJwURvoIH=w143-h110",
  "local_image": "image.jpg",
  "folder": "belts_1593",
  "raw_cells": {
    "col_0": {
      "text": "50"
    },
    "col_1": {
      "text": "Tom Ford"
    },
    "col_2": {
      "text": "",
      "image": "https://docs.google.com/sheets-images-rt/AEjM2AxQVAkFSQvaFpCCmxGfiX5F162ygC3DMbEPZ84QF5gIcvViJlgGX_coMD6tsHWmTM8jkTWgN8JXU29ttvSKUPBjhy3KvKpIOxXKELq3D4wSBPgisf0rqt678ojZHQz1eFjM_OlwJwURvoIH=w143-h110"
    },
    "col_3": {
      "text": "MissChen",
      "links": [
        {
          "label": "MissChen",
          "url": "https://www.oopbuy.com/product/weidian/6078351381?inviteCode=29TOTHGNH"
        }
      ]
    },
    "col_5": {
      "text": "36$"
    },
    "col_7": {
      "text": "QC Pics",
      "links": [
        {
          "label": "QC Pics",
          "url": "https://www.uufinds.com/goodItemDetail/qc/1920323066922610690?action=discord&type=1&cid=1942512167859859457"
        }
      ]
    }
  }
}