{
  "name": "Acne StudiosCamouflage Jeans",
  "category": "Clothes",
  "subcategory": "",
  "best_batch": "i795",
  "best_batch_links": [
    {
      "label": "i795",
      "url": "https://www.litbuy.com/product-detail?url=https%3A%2F%2Foopbuy.com%2Fproduct%2F1%2F799544942560%3FinviteCode%3D29TOTHGNH&inviteCode=REPTARO",
      "original_url": "https://oopbuy.com/product/1/799544942560?inviteCode=29TOTHGNH"
    }
  ],
  "budget_batch": "",
  "budget_batch_links": [],
  "best_price": "47$",
  "budget_price": "",
  "pics_text": "QC Pics",
  "pics_links": [
    {
      "label": "QC Pics",
      "url": "https://www.uufinds.com/goodItemDetail/qc/1946374618246385666?action=discord&cid=1942512167859859457"
    }
  ],
  "notes": "",
  "image_url": "https://docs.google.com/sheets-images-rt/AEjM2AwzrQqroiG90anOWo-zabXJ4KAC2a4lH7jCjGUjCs6vWjYWhY1Uoveg-Z7IeUNX-b4IQVlJTyM2bKM_IFcliNWteFbRKM4o3Bh702c2qHMObPeK1DhWvkkPauc368GSX-RNrD8KyVSrUg=w143-h110",
  "raw_cells": {
    "col_0": {
      "text": "716"
    },
    "col_1": {
      "text": "Acne StudiosCamouflage Jeans"
    },
    "col_2": {
      "text": "",
      "image": "https://docs.google.com/sheets-images-rt/AEjM2AwzrQqroiG90anOWo-zabXJ4KAC2a4lH7jCjGUjCs6vWjYWhY1Uoveg-Z7IeUNX-b4IQVlJTyM2bKM_IFcliNWteFbRKM4o3Bh702c2qHMObPeK1DhWvkkPauc368GSX-RNrD8KyVSrUg=w143-h110"
    },
    "col_3": {
      "text": "i795",
      "links": [
        {
          "label": "i795",
          "url": "https://oopbuy.com/product/1/799544942560?inviteCode=29TOTHGNH"
        }
      ]
    },
    "col_5": {
      "text": "47$"
    },
    "col_7": {
      "text": "QC Pics",
      "links": [
        {
          "label": "QC Pics",
          "url": "https://www.uufinds.com/goodItemDetail/qc/1946374618246385666?action=discord&cid=1942512167859859457"
        }
      ]
    }
  },
  "local_image": "image.jpg",
  "folder": "clothes_1153"
}