{
  "name": "BalenciagaTrompe L'oeilBoxer Sweatpants",
  "category": "Clothes",
  "subcategory": "",
  "best_batch": "mvt-shop01/2Three",
  "best_batch_links": [
    {
      "label": "mvt-shop01",
      "url": "https://litbuy.com/product/weidian/1009307628825?inviteCode=REPTARO",
      "original_url": "https://weidian.com/item.html?itemID=1009307628825"
    },
    {
      "label": "2Three",
      "url": "https://litbuy.com/product/weidian/788109279156?inviteCode=REPTARO",
      "original_url": "https://weidian.com/item.html?itemID=788109279156"
    }
  ],
  "budget_batch": "budget",
  "budget_batch_links": [
    {
      "label": "budget",
      "url": "https://litbuy.com/product/weidian/908581249801?inviteCode=REPTARO",
      "original_url": "https://weidian.com/item.html?itemID=908581249801"
    }
  ],
  "best_price": "57$ / 54$",
  "budget_price": "31$",
  "pics_text": "mvt/2Three/budget",
  "pics_links": [
    {
      "label": "mvt",
      "url": "https://mvt-shop01.x.yupoo.com/albums/210269652?uid=1"
    },
    {
      "label": "2Three",
      "url": "https://www.uufinds.com/goodItemDetail/qc/1889875552720961544?action=discord&cid=1840597081113280514"
    },
    {
      "label": "budget",
      "url": "https://www.uufinds.com/goodItemDetail/qc/2006222297835327489?action=discord&type=1&cid=1942512167859859457"
    }
  ],
  "notes": "",
  "image_url": "https://docs.google.com/sheets-images-rt/AEjM2AzczL7vwixoKjnR6AN47_qRd9LCVPUywRJFb3hGonT_YRBcnVmuh9qZ138piGmgl0rRrotPw9Dx9HUp6ZKq6Y7wc07R9NNWxlR1aq3RYmiXS9vrjQpQCEesUnJpyAKYkDlSrh27UyD-ag=w143-h110",
  "local_image": "image.jpg",
  "folder": "clothes_1271",
  "raw_cells": {
    "col_0": {
      "text": "856"
    },
    "col_1": {
      "text": "BalenciagaTrompe L'oeilBoxer Sweatpants"
    },
    "col_2": {
      "text": "",
      "image": "https://docs.google.com/sheets-images-rt/AEjM2AzczL7vwixoKjnR6AN47_qRd9LCVPUywRJFb3hGonT_YRBcnVmuh9qZ138piGmgl0rRrotPw9Dx9HUp6ZKq6Y7wc07R9NNWxlR1aq3RYmiXS9vrjQpQCEesUnJpyAKYkDlSrh27UyD-ag=w143-h110"
    },
    "col_3": {
      "text": "mvt-shop01/2Three",
      "links": [
        {
          "label": "mvt-shop01",
          "url": "https://litbuy.com/product/weidian/1009307628825?inviteCode=REPTARO",
          "original_url": "https://weidian.com/item.html?itemID=1009307628825"
        },
        {
          "label": "2Three",
          "url": "https://litbuy.com/product/weidian/788109279156?inviteCode=REPTARO",
          "original_url": "https://weidian.com/item.html?itemID=788109279156"
        }
      ]
    },
    "col_4": {
      "text": "budget",
      "links": [
        {
          "label": "budget",
          "url": "https://litbuy.com/product/weidian/908581249801?inviteCode=REPTARO",
          "original_url": "https://weidian.com/item.html?itemID=908581249801"
        }
      ]
    },
    "col_5": {
      "text": "57$ / 54$"
    },
    "col_6": {
      "text": "31$"
    },
    "col_7": {
      "text": "mvt/2Three/budget",
      "links": [
        {
          "label": "mvt",
          "url": "https://mvt-shop01.x.yupoo.com/albums/210269652?uid=1"
        },
        {
          "label": "2Three",
          "url": "https://www.uufinds.com/goodItemDetail/qc/1889875552720961544?action=discord&cid=1840597081113280514"
        },
        {
          "label": "budget",
          "url": "https://www.uufinds.com/goodItemDetail/qc/2006222297835327489?action=discord&type=1&cid=1942512167859859457"
        }
      ]
    }
  }
}