{
  "name": "SupremeThrasherBeanie",
  "category": "Clothes",
  "subcategory": "",
  "best_batch": "DRAGONREP",
  "best_batch_links": [
    {
      "label": "DRAGONREP",
      "url": "https://litbuy.com/product/weidian/7589573963?inviteCode=REPTARO",
      "original_url": "https://weidian.com/item.html?itemID=7589573963"
    }
  ],
  "budget_batch": "",
  "budget_batch_links": [],
  "best_price": "9$",
  "budget_price": "",
  "pics_text": "pics",
  "pics_links": [
    {
      "label": "pics",
      "url": "https://noghost.x.yupoo.com/albums/179537843?uid=1"
    }
  ],
  "notes": "",
  "image_url": "https://docs.google.com/sheets-images-rt/AEjM2Awza7WSC76tvsHrZhIyE2RV_Wpttropo9AnPdI1bzXkf2_0OwMEwzAPf6tAXTTK5nPBDSZSw-pI84eT35EHuXqxie1Drh9Pnv-DNN6w2Etb_PkuXryKgvoPEink09lD8eeCFiQcTH6fFA=w143-h110",
  "local_image": "image.jpg",
  "folder": "clothes_1198",
  "raw_cells": {
    "col_0": {
      "text": "763"
    },
    "col_1": {
      "text": "SupremeThrasherBeanie"
    },
    "col_2": {
      "text": "",
      "image": "https://docs.google.com/sheets-images-rt/AEjM2Awza7WSC76tvsHrZhIyE2RV_Wpttropo9AnPdI1bzXkf2_0OwMEwzAPf6tAXTTK5nPBDSZSw-pI84eT35EHuXqxie1Drh9Pnv-DNN6w2Etb_PkuXryKgvoPEink09lD8eeCFiQcTH6fFA=w143-h110"
    },
    "col_3": {
      "text": "DRAGONREP",
      "links": [
        {
          "label": "DRAGONREP",
          "url": "https://weidian.com/item.html?itemID=7589573963"
        }
      ]
    },
    "col_5": {
      "text": "9$"
    },
    "col_7": {
      "text": "pics",
      "links": [
        {
          "label": "pics",
          "url": "https://noghost.x.yupoo.com/albums/179537843?uid=1"
        }
      ]
    }
  }
}