{
  "name": "Nike Elite",
  "category": "Wallets/Bags",
  "subcategory": "",
  "best_batch": "",
  "best_batch_links": [],
  "budget_batch": "budget",
  "budget_batch_links": [
    {
      "label": "budget",
      "url": "https://litbuy.com/product/taobao/2225747304?inviteCode=REPTARO",
      "original_url": "https://item.taobao.com/item.htm?id=2225747304"
    }
  ],
  "best_price": "",
  "budget_price": "15$",
  "pics_text": "QC Pics",
  "pics_links": [
    {
      "label": "QC Pics",
      "url": "https://www.uufinds.com/goodItemDetail/qc/1973574392350334977?action=discord&type=1&cid=1942512167859859457"
    }
  ],
  "notes": "",
  "image_url": "https://docs.google.com/sheets-images-rt/AEjM2Aw1unnEOqfyTJxsbkNG69iT_Wsd6p5feT1zj_QpPaDj0cF9ycrQYJ7Xnj39VrzJhenuaKxvgFJOKZLPqe1xoQix84bCf2wmYe6SRtd-DEpWEoEBIMTTALx8vfGbs0KzNfW7eLU7rcpzIA=w143-h110",
  "local_image": "image.jpg",
  "folder": "walletsbags_1545",
  "raw_cells": {
    "col_0": {
      "text": "47"
    },
    "col_1": {
      "text": "Nike Elite"
    },
    "col_2": {
      "text": "",
      "image": "https://docs.google.com/sheets-images-rt/AEjM2Aw1unnEOqfyTJxsbkNG69iT_Wsd6p5feT1zj_QpPaDj0cF9ycrQYJ7Xnj39VrzJhenuaKxvgFJOKZLPqe1xoQix84bCf2wmYe6SRtd-DEpWEoEBIMTTALx8vfGbs0KzNfW7eLU7rcpzIA=w143-h110"
    },
    "col_4": {
      "text": "budget",
      "links": [
        {
          "label": "budget",
          "url": "https://item.taobao.com/item.htm?id=2225747304"
        }
      ]
    },
    "col_6": {
      "text": "15$"
    },
    "col_7": {
      "text": "QC Pics",
      "links": [
        {
          "label": "QC Pics",
          "url": "https://www.uufinds.com/goodItemDetail/qc/1973574392350334977?action=discord&type=1&cid=1942512167859859457"
        }
      ]
    }
  }
}