{
  "name": "BAPE SK8 Sta",
  "category": "Shoes",
  "subcategory": "",
  "best_batch": "Version1",
  "best_batch_links": [
    {
      "label": "Version1",
      "url": "https://litbuy.com/product/weidian/7563983179?inviteCode=REPTARO",
      "original_url": "https://oopbuy.com/product/weidian/7563983179?inviteCode=29TOTHGNH"
    }
  ],
  "budget_batch": "",
  "budget_batch_links": [],
  "best_price": "53$",
  "budget_price": "",
  "pics_text": "",
  "pics_links": [],
  "notes": "",
  "image_url": "https://docs.google.com/sheets-images-rt/AEjM2Aze-jzMSkxfZYH5HGPKOcsGLgWGhFmIxd3mTYlfazqXwwCPxZkSszb0gsxYjvNNVi1-ET9NpczwmJrLfGyy8ZxvQ4ejorklOzaTBa4UWNALtkRFdtNEmgU5I0C2LaCfksXiLNfnfzbywf7J=w143-h110",
  "local_image": "image.jpg",
  "folder": "shoes_0385",
  "raw_cells": {
    "col_0": {
      "text": "426"
    },
    "col_1": {
      "text": "BAPE SK8 Sta"
    },
    "col_2": {
      "text": "",
      "image": "https://docs.google.com/sheets-images-rt/AEjM2Aze-jzMSkxfZYH5HGPKOcsGLgWGhFmIxd3mTYlfazqXwwCPxZkSszb0gsxYjvNNVi1-ET9NpczwmJrLfGyy8ZxvQ4ejorklOzaTBa4UWNALtkRFdtNEmgU5I0C2LaCfksXiLNfnfzbywf7J=w143-h110"
    },
    "col_3": {
      "text": "Version1",
      "links": [
        {
          "label": "Version1",
          "url": "https://oopbuy.com/product/weidian/7563983179?inviteCode=29TOTHGNH"
        }
      ]
    },
    "col_5": {
      "text": "53$"
    }
  }
}