{
  "name": "VetementsShut Up!Zip Up Hoodie",
  "category": "Clothes",
  "subcategory": "",
  "best_batch": "mvt-shop01",
  "best_batch_links": [
    {
      "label": "mvt-shop01",
      "url": "https://www.litbuy.com/product-detail?url=https%3A%2F%2Foopbuy.com%2Fproduct%2F1%2F838039010255%3FinviteCode%3D29TOTHGNH&inviteCode=REPTARO",
      "original_url": "https://oopbuy.com/product/1/838039010255?inviteCode=29TOTHGNH"
    }
  ],
  "budget_batch": "",
  "budget_batch_links": [],
  "best_price": "60$",
  "budget_price": "",
  "pics_text": "pics",
  "pics_links": [
    {
      "label": "pics",
      "url": "https://mvt-shop01.x.yupoo.com/albums/190713228?uid=1&isSubCate=false&referrercate=4736074"
    }
  ],
  "notes": "",
  "image_url": "https://docs.google.com/sheets-images-rt/AEjM2Ax9M6vrrd1QpKUTBKp3nXH57MzPZ-SIWS1llp10BVnvZbdvrZ_fzUHmcAXyCmH8nRaQ2ei6ALetmn90_e_wydoiyaZBISWOci_OX-qO8ir1MbWkXdMtHSDdJA0nNfrLVWP2DsMisLTy0A=w143-h110",
  "raw_cells": {
    "col_0": {
      "text": "678"
    },
    "col_1": {
      "text": "VetementsShut Up!Zip Up Hoodie"
    },
    "col_2": {
      "text": "",
      "image": "https://docs.google.com/sheets-images-rt/AEjM2Ax9M6vrrd1QpKUTBKp3nXH57MzPZ-SIWS1llp10BVnvZbdvrZ_fzUHmcAXyCmH8nRaQ2ei6ALetmn90_e_wydoiyaZBISWOci_OX-qO8ir1MbWkXdMtHSDdJA0nNfrLVWP2DsMisLTy0A=w143-h110"
    },
    "col_3": {
      "text": "mvt-shop01",
      "links": [
        {
          "label": "mvt-shop01",
          "url": "https://oopbuy.com/product/1/838039010255?inviteCode=29TOTHGNH"
        }
      ]
    },
    "col_5": {
      "text": "60$"
    },
    "col_7": {
      "text": "pics",
      "links": [
        {
          "label": "pics",
          "url": "https://mvt-shop01.x.yupoo.com/albums/190713228?uid=1&isSubCate=false&referrercate=4736074"
        }
      ]
    }
  },
  "local_image": "image.jpg",
  "folder": "clothes_1123"
}