{
  "name": "ZaraFlared Jeans3 Colors",
  "category": "Clothes",
  "subcategory": "",
  "best_batch": "",
  "best_batch_links": [],
  "budget_batch": "ZABA",
  "budget_batch_links": [
    {
      "label": "ZABA",
      "url": "https://www.litbuy.com/product-detail?url=https%3A%2F%2Foopbuy.com%2Fproduct%2F1%2F908665888932%3FinviteCode%3D29TOTHGNH&inviteCode=REPTARO",
      "original_url": "https://oopbuy.com/product/1/908665888932?inviteCode=29TOTHGNH"
    }
  ],
  "best_price": "",
  "budget_price": "18$",
  "pics_text": "QC Pics",
  "pics_links": [
    {
      "label": "QC Pics",
      "url": "https://www.uufinds.com/goodItemDetail/qc/2001479149410144258?action=discord&type=1&cid=1942512167859859457"
    }
  ],
  "notes": "",
  "image_url": "https://docs.google.com/sheets-images-rt/AEjM2AzY018Atr1HBalBqEQQjW2tNYYt7iOesK8YxM4zLcZkLzEBqPMJREfaInNw9Xhtiu8IugQujmnZuW_FnZEXqOU1EqgBEbYGgmt93e_1IvPpeuHIyu2sm8qWUcHKkFHmqqi7d30MuK0JpC-H=w143-h110",
  "raw_cells": {
    "col_0": {
      "text": "823"
    },
    "col_1": {
      "text": "ZaraFlared Jeans3 Colors"
    },
    "col_2": {
      "text": "",
      "image": "https://docs.google.com/sheets-images-rt/AEjM2AzY018Atr1HBalBqEQQjW2tNYYt7iOesK8YxM4zLcZkLzEBqPMJREfaInNw9Xhtiu8IugQujmnZuW_FnZEXqOU1EqgBEbYGgmt93e_1IvPpeuHIyu2sm8qWUcHKkFHmqqi7d30MuK0JpC-H=w143-h110"
    },
    "col_4": {
      "text": "ZABA",
      "links": [
        {
          "label": "ZABA",
          "url": "https://oopbuy.com/product/1/908665888932?inviteCode=29TOTHGNH"
        }
      ]
    },
    "col_6": {
      "text": "18$"
    },
    "col_7": {
      "text": "QC Pics",
      "links": [
        {
          "label": "QC Pics",
          "url": "https://www.uufinds.com/goodItemDetail/qc/2001479149410144258?action=discord&type=1&cid=1942512167859859457"
        }
      ]
    }
  },
  "local_image": "image.jpg",
  "folder": "clothes_1240"
}