{
  "name": "327",
  "category": "Shoes",
  "subcategory": "",
  "best_batch": "M",
  "best_batch_links": [
    {
      "label": "M",
      "url": "https://litbuy.com/product/taobao/7255346568?inviteCode=REPTARO",
      "original_url": "https://item.taobao.com/item.htm?id=7255346568"
    }
  ],
  "budget_batch": "",
  "budget_batch_links": [],
  "best_price": "32$",
  "budget_price": "",
  "pics_text": "",
  "pics_links": [],
  "notes": "",
  "image_url": "https://docs.google.com/sheets-images-rt/AEjM2AwouOGXy3XRgVEI1FEz8XahBB8apbXy60YiSZQuNkgh1kNDyxFFoUplZZnPOkOMcyR9VCoIFkJQC-z1H3j8F_pt7I4gLufv5DP2HDrxXaeVpiaWGDEPxv65lFNhwSP5z4EMr2sxFIU12fx-=w143-h110",
  "local_image": "image.jpg",
  "folder": "shoes_0363",
  "raw_cells": {
    "col_0": {
      "text": "396"
    },
    "col_1": {
      "text": "327"
    },
    "col_2": {
      "text": "",
      "image": "https://docs.google.com/sheets-images-rt/AEjM2AwouOGXy3XRgVEI1FEz8XahBB8apbXy60YiSZQuNkgh1kNDyxFFoUplZZnPOkOMcyR9VCoIFkJQC-z1H3j8F_pt7I4gLufv5DP2HDrxXaeVpiaWGDEPxv65lFNhwSP5z4EMr2sxFIU12fx-=w143-h110"
    },
    "col_3": {
      "text": "M",
      "links": [
        {
          "label": "M",
          "url": "https://litbuy.com/product/taobao/7255346568?inviteCode=REPTARO",
          "original_url": "https://item.taobao.com/item.htm?id=7255346568"
        }
      ]
    },
    "col_5": {
      "text": "32$"
    }
  }
}